{"result":{"totalrows":475,"rows":[{"rownum":1,"values":[{"field":"querydate","value":"6/16/2016 10:46 PM"},{"field":"issueid","value":469102},{"field":"ticker","value":"AMG"},{"field":"companyname","value":"AFFILIATED MANAGERS GROUP"},{"field":"issuetitle","value":"COM"},{"field":"filerid","value":61322},{"field":"cik","value":"0000102909"},{"field":"currentreportdate","value":"3/31/2016 12:00 AM"},{"field":"priorreportdate","value":"12/31/2015 12:00 AM"},{"field":"ownername","value":"VANGUARD GROUP INC"},{"field":"street1","value":"PO BOX 2600"},{"field":"street2","value":"V26"},{"field":"street3","value":null},{"field":"city","value":"VALLEY FORGE"},{"field":"state","value":"PA"},{"field":"zip","value":"19482-2600"},{"field":"phone","value":"6106691000"},{"field":"sharesheld","value":4661060.0},{"field":"sharesheldchange","value":110400.0},{"field":"sharesheldpercentchange","value":0.024260217199263405},{"field":"marketvalue","value":717057470.0},{"field":"marketvaluechange","value":16983936.0},{"field":"portfoliopercent","value":0.000461536316756463},{"field":"sharesoutpercent","value":0.086618207429445912}]},{"rownum":2,"values":[{"field":"querydate","value":"6/16/2016 10:46 PM"},{"field":"issueid","value":469102},{"field":"ticker","value":"AMG"},{"field":"companyname","value":"AFFILIATED MANAGERS GROUP"},{"field":"issuetitle","value":"COM"},{"field":"filerid","value":6697},{"field":"cik","value":"0000093751"},{"field":"currentreportdate","value":"3/31/2016 12:00 AM"},{"field":"priorreportdate","value":"12/31/2015 12:00 AM"},{"field":"ownername","value":"STATE STREET CORP"},{"field":"street1","value":"ONE LINCOLN STREET"},{"field":"street2","value":null},{"field":"street3","value":null},{"field":"city","value":"BOSTON"},{"field":"state","value":"MA"},{"field":"zip","value":"02111"},{"field":"phone","value":"617 786-3000"},{"field":"sharesheld","value":2266925.0},{"field":"sharesheldchange","value":-106733.0},{"field":"sharesheldpercentchange","value":-0.04496561846736135},{"field":"marketvalue","value":348743742.0},{"field":"marketvaluechange","value":-16419804.72},{"field":"portfoliopercent","value":0.000374617782680483},{"field":"sharesoutpercent","value":0.042127108399590794}]},{"rownum":3,"values":[{"field":"querydate","value":"6/16/2016 10:46 PM"},{"field":"issueid","value":469102},{"field":"ticker","value":"AMG"},{"field":"companyname","value":"AFFILIATED MANAGERS GROUP"},{"field":"issuetitle","value":"COM"},{"field":"filerid","value":976905},{"field":"cik","value":"0001644956"},{"field":"currentreportdate","value":"3/31/2016 12:00 AM"},{"field":"priorreportdate","value":"12/31/2015 12:00 AM"},{"field":"ownername","value":"WILLIAM BLAIR INVESTMENT MANAGEMENT, LLC"},{"field":"street1","value":"222 WEST ADAMS STREET"},{"field":"street2","value":null},{"field":"street3","value":null},{"field":"city","value":"CHICAGO"},{"field":"state","value":"IL"},{"field":"zip","value":"60606"},{"field":"phone","value":"3122361600"},{"field":"sharesheld","value":2198830.0},{"field":"sharesheldchange","value":-113785.0},{"field":"sharesheldpercentchange","value":-0.049201877528252648},{"field":"marketvalue","value":338268007.0},{"field":"marketvaluechange","value":-17504684.4},{"field":"portfoliopercent","value":0.013355498960727278},{"field":"sharesoutpercent","value":0.040861673748479647}]},{"rownum":4,"values":[{"field":"querydate","value":"6/16/2016 10:46 PM"},{"field":"issueid","value":469102},{"field":"ticker","value":"AMG"},{"field":"companyname","value":"AFFILIATED MANAGERS GROUP"},{"field":"issuetitle","value":"COM"},{"field":"filerid","value":2145},{"field":"cik","value":"0000080255"},{"field":"currentreportdate","value":"3/31/2016 12:00 AM"},{"field":"priorreportdate","value":"12/31/2015 12:00 AM"},{"field":"ownername","value":"PRICE T ROWE ASSOCIATES INC /MD/"},{"field":"street1","value":"100 EAST PRATT ST"},{"field":"street2","value":null},{"field":"street3","value":null},{"field":"city","value":"BALTIMORE"},{"field":"state","value":"MD"},{"field":"zip","value":"21202"},{"field":"phone","value":"(410)345-6603"},{"field":"sharesheld","value":2141683.0},{"field":"sharesheldchange","value":902044.0},{"field":"sharesheldpercentchange","value":0.72766668360708242},{"field":"marketvalue","value":329476513.0},{"field":"marketvaluechange","value":138770448.96},{"field":"portfoliopercent","value":0.000693584721810016},{"field":"sharesoutpercent","value":0.039799689843537309}]},{"rownum":5,"values":[{"field":"querydate","value":"6/16/2016 10:46 PM"},{"field":"issueid","value":469102},{"field":"ticker","value":"AMG"},{"field":"companyname","value":"AFFILIATED MANAGERS GROUP"},{"field":"issuetitle","value":"COM"},{"field":"filerid","value":64045},{"field":"cik","value":"0001027817"},{"field":"currentreportdate","value":"3/31/2016 12:00 AM"},{"field":"priorreportdate","value":"12/31/2015 12:00 AM"},{"field":"ownername","value":"ATLANTA CAPITAL MANAGEMENT CO L L C"},{"field":"street1","value":"1075 PEACHTREE STREET"},{"field":"street2","value":"SUITE 2100"},{"field":"street3","value":null},{"field":"city","value":"ATLANTA"},{"field":"state","value":"GA"},{"field":"zip","value":"30309"},{"field":"phone","value":"4048769411"},{"field":"sharesheld","value":1715527.0},{"field":"sharesheldchange","value":500978.0},{"field":"sharesheldpercentchange","value":0.41248068212974526},{"field":"marketvalue","value":263916674.0},{"field":"marketvaluechange","value":77070455.52},{"field":"portfoliopercent","value":0.018524691351315774},{"field":"sharesoutpercent","value":0.031880274773724231}]},{"rownum":6,"values":[{"field":"querydate","value":"6/16/2016 10:46 PM"},{"field":"issueid","value":469102},{"field":"ticker","value":"AMG"},{"field":"companyname","value":"AFFILIATED MANAGERS GROUP"},{"field":"issuetitle","value":"COM"},{"field":"filerid","value":11158},{"field":"cik","value":"0000886982"},{"field":"currentreportdate","value":"3/31/2016 12:00 AM"},{"field":"priorreportdate","value":"12/31/2015 12:00 AM"},{"field":"ownername","value":"GOLDMAN SACHS GROUP INC"},{"field":"street1","value":"200 WEST STREET"},{"field":"street2","value":null},{"field":"street3","value":null},{"field":"city","value":"NEW YORK"},{"field":"state","value":"NY"},{"field":"zip","value":"10282"},{"field":"phone","value":"2129021000"},{"field":"sharesheld","value":1491212.0},{"field":"sharesheldchange","value":-646776.0},{"field":"sharesheldpercentchange","value":-0.30251619747164155},{"field":"marketvalue","value":229408054.0},{"field":"marketvaluechange","value":-99500019.84},{"field":"portfoliopercent","value":0.000932542545323881},{"field":"sharesoutpercent","value":0.027711745898417718}]},{"rownum":7,"values":[{"field":"querydate","value":"6/16/2016 10:46 PM"},{"field":"issueid","value":469102},{"field":"ticker","value":"AMG"},{"field":"companyname","value":"AFFILIATED MANAGERS GROUP"},{"field":"issuetitle","value":"COM"},{"field":"filerid","value":12291},{"field":"cik","value":"0000914208"},{"field":"currentreportdate","value":"3/31/2016 12:00 AM"},{"field":"priorreportdate","value":"12/31/2015 12:00 AM"},{"field":"ownername","value":"INVESCO LTD."},{"field":"street1","value":"1555 PEACHTREE STREET NE"},{"field":"street2","value":"SUITE 1800"},{"field":"street3","value":null},{"field":"city","value":"ATLANTA"},{"field":"state","value":"GA"},{"field":"zip","value":"30309"},{"field":"phone","value":"404-892-0896"},{"field":"sharesheld","value":1406025.0},{"field":"sharesheldchange","value":538494.0},{"field":"sharesheldpercentchange","value":0.62072018175719368},{"field":"marketvalue","value":216302886.0},{"field":"marketvaluechange","value":82841916.96},{"field":"portfoliopercent","value":0.000899130200489375},{"field":"sharesoutpercent","value":0.026128684269455162}]},{"rownum":8,"values":[{"field":"querydate","value":"6/16/2016 10:46 PM"},{"field":"issueid","value":469102},{"field":"ticker","value":"AMG"},{"field":"companyname","value":"AFFILIATED MANAGERS GROUP"},{"field":"issuetitle","value":"COM"},{"field":"filerid","value":37652},{"field":"cik","value":"0000913414"},{"field":"currentreportdate","value":"3/31/2016 12:00 AM"},{"field":"priorreportdate","value":"12/31/2015 12:00 AM"},{"field":"ownername","value":"BLACKROCK INSTITUTIONAL TRUST COMPANY, N.A."},{"field":"street1","value":"400 HOWARD STREET"},{"field":"street2","value":null},{"field":"street3","value":null},{"field":"city","value":"SAN FRANCISCO"},{"field":"state","value":"CA"},{"field":"zip","value":"94105"},{"field":"phone","value":"4155972639"},{"field":"sharesheld","value":1391471.0},{"field":"sharesheldchange","value":-177980.0},{"field":"sharesheldpercentchange","value":-0.11340271215858284},{"field":"marketvalue","value":214063899.0},{"field":"marketvaluechange","value":-27380443.2},{"field":"portfoliopercent","value":0.000351257552764019},{"field":"sharesoutpercent","value":0.025858221887308581}]},{"rownum":9,"values":[{"field":"querydate","value":"6/16/2016 10:46 PM"},{"field":"issueid","value":469102},{"field":"ticker","value":"AMG"},{"field":"companyname","value":"AFFILIATED MANAGERS GROUP"},{"field":"issuetitle","value":"COM"},{"field":"filerid","value":8130},{"field":"cik","value":"0000072971"},{"field":"currentreportdate","value":"3/31/2016 12:00 AM"},{"field":"priorreportdate","value":"12/31/2015 12:00 AM"},{"field":"ownername","value":"WELLS FARGO & COMPANY/MN"},{"field":"street1","value":"420 MONTGOMERY STREET"},{"field":"street2","value":null},{"field":"street3","value":null},{"field":"city","value":"SAN FRANCISCO"},{"field":"state","value":"CA"},{"field":"zip","value":"94163"},{"field":"phone","value":"6126671234"},{"field":"sharesheld","value":1351315.0},{"field":"sharesheldchange","value":353024.0},{"field":"sharesheldpercentchange","value":0.35362835085160538},{"field":"marketvalue","value":207886300.0},{"field":"marketvaluechange","value":54309212.16},{"field":"portfoliopercent","value":0.000825079541614107},{"field":"sharesoutpercent","value":0.0251119880397424}]},{"rownum":10,"values":[{"field":"querydate","value":"6/16/2016 10:46 PM"},{"field":"issueid","value":469102},{"field":"ticker","value":"AMG"},{"field":"companyname","value":"AFFILIATED MANAGERS GROUP"},{"field":"issuetitle","value":"COM"},{"field":"filerid","value":15519},{"field":"cik","value":"0000070858"},{"field":"currentreportdate","value":"3/31/2016 12:00 AM"},{"field":"priorreportdate","value":"12/31/2015 12:00 AM"},{"field":"ownername","value":"BANK OF AMERICA CORP /DE/"},{"field":"street1","value":"BANK OF AMERICA CORPORATE CENTER"},{"field":"street2","value":"100 N TRYON ST"},{"field":"street3","value":null},{"field":"city","value":"CHARLOTTE"},{"field":"state","value":"NC"},{"field":"zip","value":"28255"},{"field":"phone","value":"7043868486"},{"field":"sharesheld","value":1277876.0},{"field":"sharesheldchange","value":73482.0},{"field":"sharesheldpercentchange","value":0.061011595873111293},{"field":"marketvalue","value":196588444.0},{"field":"marketvaluechange","value":11304470.88},{"field":"portfoliopercent","value":0.000519128504452761},{"field":"sharesoutpercent","value":0.02374724385378232}]}]}}