{"result":{"totalrows":556,"rows":[{"rownum":1,"values":[{"field":"querydate","value":"6/16/2016 11:06 PM"},{"field":"issueid","value":532219},{"field":"ticker","value":"DGX"},{"field":"companyname","value":"QUEST DIAGNOSTICS INC"},{"field":"issuetitle","value":"COM"},{"field":"filerid","value":61322},{"field":"cik","value":"0000102909"},{"field":"currentreportdate","value":"3/31/2016 12:00 AM"},{"field":"priorreportdate","value":"12/31/2015 12:00 AM"},{"field":"ownername","value":"VANGUARD GROUP INC"},{"field":"street1","value":"PO BOX 2600"},{"field":"street2","value":"V26"},{"field":"street3","value":null},{"field":"city","value":"VALLEY FORGE"},{"field":"state","value":"PA"},{"field":"zip","value":"19482-2600"},{"field":"phone","value":"6106691000"},{"field":"sharesheld","value":12679627.0},{"field":"sharesheldchange","value":370896.0},{"field":"sharesheldpercentchange","value":0.030132756983640312},{"field":"marketvalue","value":971513021.0},{"field":"marketvaluechange","value":28418051.52},{"field":"portfoliopercent","value":0.000625317439888443},{"field":"sharesoutpercent","value":0.089635795233076257}]},{"rownum":2,"values":[{"field":"querydate","value":"6/16/2016 11:06 PM"},{"field":"issueid","value":532219},{"field":"ticker","value":"DGX"},{"field":"companyname","value":"QUEST DIAGNOSTICS INC"},{"field":"issuetitle","value":"COM"},{"field":"filerid","value":762271},{"field":"cik","value":"0001418333"},{"field":"currentreportdate","value":"3/31/2016 12:00 AM"},{"field":"priorreportdate","value":"12/31/2015 12:00 AM"},{"field":"ownername","value":"MACQUARIE GROUP LTD"},{"field":"street1","value":"50 MARTIN PLACE"},{"field":"street2","value":null},{"field":"street3","value":null},{"field":"city","value":"SYDNEY, NSW 2000"},{"field":"state","value":null},{"field":"zip","value":"2000"},{"field":"phone","value":"212.231.1000"},{"field":"sharesheld","value":9896641.0},{"field":"sharesheldchange","value":550992.0},{"field":"sharesheldpercentchange","value":0.058957061195001013},{"field":"marketvalue","value":758280633.0},{"field":"marketvaluechange","value":42217007.04},{"field":"portfoliopercent","value":0.014725806340830287},{"field":"sharesoutpercent","value":0.069962096374859215}]},{"rownum":3,"values":[{"field":"querydate","value":"6/16/2016 11:06 PM"},{"field":"issueid","value":532219},{"field":"ticker","value":"DGX"},{"field":"companyname","value":"QUEST DIAGNOSTICS INC"},{"field":"issuetitle","value":"COM"},{"field":"filerid","value":6697},{"field":"cik","value":"0000093751"},{"field":"currentreportdate","value":"3/31/2016 12:00 AM"},{"field":"priorreportdate","value":"12/31/2015 12:00 AM"},{"field":"ownername","value":"STATE STREET CORP"},{"field":"street1","value":"ONE LINCOLN STREET"},{"field":"street2","value":null},{"field":"street3","value":null},{"field":"city","value":"BOSTON"},{"field":"state","value":"MA"},{"field":"zip","value":"02111"},{"field":"phone","value":"617 786-3000"},{"field":"sharesheld","value":6129848.0},{"field":"sharesheldchange","value":-33973.0},{"field":"sharesheldpercentchange","value":-0.0055116785513401514},{"field":"marketvalue","value":469668954.0},{"field":"marketvaluechange","value":-2603011.26},{"field":"portfoliopercent","value":0.000504514693603712},{"field":"sharesoutpercent","value":0.043333593341340564}]},{"rownum":4,"values":[{"field":"querydate","value":"6/16/2016 11:06 PM"},{"field":"issueid","value":532219},{"field":"ticker","value":"DGX"},{"field":"companyname","value":"QUEST DIAGNOSTICS INC"},{"field":"issuetitle","value":"COM"},{"field":"filerid","value":887648},{"field":"cik","value":"0001535323"},{"field":"currentreportdate","value":"3/31/2016 12:00 AM"},{"field":"priorreportdate","value":"12/31/2015 12:00 AM"},{"field":"ownername","value":"ALLIANZ ASSET MANAGEMENT AG"},{"field":"street1","value":"SEIDLSTRASSE 24-24A"},{"field":"street2","value":null},{"field":"street3","value":null},{"field":"city","value":"MUNICH"},{"field":"state","value":null},{"field":"zip","value":"D-80335"},{"field":"phone","value":"49 89 1220 70"},{"field":"sharesheld","value":4506752.0},{"field":"sharesheldchange","value":318345.0},{"field":"sharesheldpercentchange","value":0.0760062238459634},{"field":"marketvalue","value":345307338.0},{"field":"marketvaluechange","value":24391593.9},{"field":"portfoliopercent","value":0.0047776917994902949},{"field":"sharesoutpercent","value":0.031859478156436062}]},{"rownum":5,"values":[{"field":"querydate","value":"6/16/2016 11:06 PM"},{"field":"issueid","value":532219},{"field":"ticker","value":"DGX"},{"field":"companyname","value":"QUEST DIAGNOSTICS INC"},{"field":"issuetitle","value":"COM"},{"field":"filerid","value":37652},{"field":"cik","value":"0000913414"},{"field":"currentreportdate","value":"3/31/2016 12:00 AM"},{"field":"priorreportdate","value":"12/31/2015 12:00 AM"},{"field":"ownername","value":"BLACKROCK INSTITUTIONAL TRUST COMPANY, N.A."},{"field":"street1","value":"400 HOWARD STREET"},{"field":"street2","value":null},{"field":"street3","value":null},{"field":"city","value":"SAN FRANCISCO"},{"field":"state","value":"CA"},{"field":"zip","value":"94105"},{"field":"phone","value":"4155972639"},{"field":"sharesheld","value":4200612.0},{"field":"sharesheldchange","value":286330.0},{"field":"sharesheldpercentchange","value":0.073150069412474622},{"field":"marketvalue","value":321850891.0},{"field":"marketvaluechange","value":21938604.6},{"field":"portfoliopercent","value":0.000528125278740153},{"field":"sharesoutpercent","value":0.029695289702575865}]},{"rownum":6,"values":[{"field":"querydate","value":"6/16/2016 11:06 PM"},{"field":"issueid","value":532219},{"field":"ticker","value":"DGX"},{"field":"companyname","value":"QUEST DIAGNOSTICS INC"},{"field":"issuetitle","value":"COM"},{"field":"filerid","value":13603},{"field":"cik","value":"0000748054"},{"field":"currentreportdate","value":"3/31/2016 12:00 AM"},{"field":"priorreportdate","value":"12/31/2015 12:00 AM"},{"field":"ownername","value":"AMERICAN CENTURY COMPANIES INC"},{"field":"street1","value":"4500 MAIN STREET"},{"field":"street2","value":null},{"field":"street3","value":null},{"field":"city","value":"KANSAS CITY"},{"field":"state","value":"MO"},{"field":"zip","value":"64111"},{"field":"phone","value":"8165315575"},{"field":"sharesheld","value":3695576.0},{"field":"sharesheldchange","value":-181298.0},{"field":"sharesheldpercentchange","value":-0.046763964988286957},{"field":"marketvalue","value":283155033.0},{"field":"marketvaluechange","value":-13891052.76},{"field":"portfoliopercent","value":0.0032887613645008139},{"field":"sharesoutpercent","value":0.026125050335019398}]},{"rownum":7,"values":[{"field":"querydate","value":"6/16/2016 11:06 PM"},{"field":"issueid","value":532219},{"field":"ticker","value":"DGX"},{"field":"companyname","value":"QUEST DIAGNOSTICS INC"},{"field":"issuetitle","value":"COM"},{"field":"filerid","value":62887},{"field":"cik","value":"0001086364"},{"field":"currentreportdate","value":"3/31/2016 12:00 AM"},{"field":"priorreportdate","value":"12/31/2015 12:00 AM"},{"field":"ownername","value":"BLACKROCK ADVISORS LLC"},{"field":"street1","value":"100 BELLEVUE PARKWAY"},{"field":"street2","value":null},{"field":"street3","value":null},{"field":"city","value":"WILMINGTON"},{"field":"state","value":"DE"},{"field":"zip","value":"19809"},{"field":"phone","value":"800-441-7762"},{"field":"sharesheld","value":3517310.0},{"field":"sharesheldchange","value":-715418.0},{"field":"sharesheldpercentchange","value":-0.16902054656004353},{"field":"marketvalue","value":269496292.0},{"field":"marketvaluechange","value":-54815327.16},{"field":"portfoliopercent","value":0.002880157529253244},{"field":"sharesoutpercent","value":0.024864838605366816}]},{"rownum":8,"values":[{"field":"querydate","value":"6/16/2016 11:06 PM"},{"field":"issueid","value":532219},{"field":"ticker","value":"DGX"},{"field":"companyname","value":"QUEST DIAGNOSTICS INC"},{"field":"issuetitle","value":"COM"},{"field":"filerid","value":62699},{"field":"cik","value":"0001050470"},{"field":"currentreportdate","value":"3/31/2016 12:00 AM"},{"field":"priorreportdate","value":"12/31/2015 12:00 AM"},{"field":"ownername","value":"LSV ASSET MANAGEMENT"},{"field":"street1","value":"155 NORTH WACKER DRIVE"},{"field":"street2","value":"SUITE 4600"},{"field":"street3","value":null},{"field":"city","value":"CHICAGO"},{"field":"state","value":"IL"},{"field":"zip","value":"60606"},{"field":"phone","value":"312-460-2443"},{"field":"sharesheld","value":3487925.0},{"field":"sharesheldchange","value":364450.0},{"field":"sharesheldpercentchange","value":0.11668094029886585},{"field":"marketvalue","value":267244814.0},{"field":"marketvaluechange","value":27924159.0},{"field":"portfoliopercent","value":0.0056083426653882771},{"field":"sharesoutpercent","value":0.024657107901386019}]},{"rownum":9,"values":[{"field":"querydate","value":"6/16/2016 11:06 PM"},{"field":"issueid","value":532219},{"field":"ticker","value":"DGX"},{"field":"companyname","value":"QUEST DIAGNOSTICS INC"},{"field":"issuetitle","value":"COM"},{"field":"filerid","value":39656},{"field":"cik","value":"0001036325"},{"field":"currentreportdate","value":"3/31/2016 12:00 AM"},{"field":"priorreportdate","value":"12/31/2015 12:00 AM"},{"field":"ownername","value":"DAVIS SELECTED ADVISERS"},{"field":"street1","value":"2949 E. ELVIRA ROAD"},{"field":"street2","value":"SUITE 101"},{"field":"street3","value":null},{"field":"city","value":"TUCSON"},{"field":"state","value":"AZ"},{"field":"zip","value":"85756"},{"field":"phone","value":"(520)806-7600"},{"field":"sharesheld","value":3314772.0},{"field":"sharesheldchange","value":-276085.0},{"field":"sharesheldpercentchange","value":-0.076885545706776956},{"field":"marketvalue","value":253977831.0},{"field":"marketvaluechange","value":-21153632.7},{"field":"portfoliopercent","value":0.01084693708218133},{"field":"sharesoutpercent","value":0.023433041384918866}]},{"rownum":10,"values":[{"field":"querydate","value":"6/16/2016 11:06 PM"},{"field":"issueid","value":532219},{"field":"ticker","value":"DGX"},{"field":"companyname","value":"QUEST DIAGNOSTICS INC"},{"field":"issuetitle","value":"COM"},{"field":"filerid","value":2145},{"field":"cik","value":"0000080255"},{"field":"currentreportdate","value":"3/31/2016 12:00 AM"},{"field":"priorreportdate","value":"12/31/2015 12:00 AM"},{"field":"ownername","value":"PRICE T ROWE ASSOCIATES INC /MD/"},{"field":"street1","value":"100 EAST PRATT ST"},{"field":"street2","value":null},{"field":"street3","value":null},{"field":"city","value":"BALTIMORE"},{"field":"state","value":"MD"},{"field":"zip","value":"21202"},{"field":"phone","value":"(410)345-6603"},{"field":"sharesheld","value":3313874.0},{"field":"sharesheldchange","value":189868.0},{"field":"sharesheldpercentchange","value":0.060777091977416174},{"field":"marketvalue","value":253909026.0},{"field":"marketvaluechange","value":14547686.16},{"field":"portfoliopercent","value":0.000534506753029956},{"field":"sharesoutpercent","value":0.023426693174193162}]}]}}