{"result":{"totalrows":806,"rows":[{"rownum":1,"values":[{"field":"querydate","value":"6/16/2016 10:58 PM"},{"field":"issueid","value":509060},{"field":"ticker","value":"JCI"},{"field":"companyname","value":"JOHNSON CTLS INC"},{"field":"issuetitle","value":"COM"},{"field":"filerid","value":61322},{"field":"cik","value":"0000102909"},{"field":"currentreportdate","value":"3/31/2016 12:00 AM"},{"field":"priorreportdate","value":"12/31/2015 12:00 AM"},{"field":"ownername","value":"VANGUARD GROUP INC"},{"field":"street1","value":"PO BOX 2600"},{"field":"street2","value":"V26"},{"field":"street3","value":null},{"field":"city","value":"VALLEY FORGE"},{"field":"state","value":"PA"},{"field":"zip","value":"19482-2600"},{"field":"phone","value":"6106691000"},{"field":"sharesheld","value":38652612.0},{"field":"sharesheldchange","value":2592931.0},{"field":"sharesheldpercentchange","value":0.071906653860859163},{"field":"marketvalue","value":1706126294.0},{"field":"marketvaluechange","value":114451974.34},{"field":"portfoliopercent","value":0.0010981536049741089},{"field":"sharesoutpercent","value":0.059615039617177193}]},{"rownum":2,"values":[{"field":"querydate","value":"6/16/2016 10:58 PM"},{"field":"issueid","value":509060},{"field":"ticker","value":"JCI"},{"field":"companyname","value":"JOHNSON CTLS INC"},{"field":"issuetitle","value":"COM"},{"field":"filerid","value":16689},{"field":"cik","value":"0000313028"},{"field":"currentreportdate","value":"3/31/2016 12:00 AM"},{"field":"priorreportdate","value":"12/31/2015 12:00 AM"},{"field":"ownername","value":"BARROW HANLEY MEWHINNEY & STRAUSS LLC"},{"field":"street1","value":"2200 ROSS AVENUE"},{"field":"street2","value":"31ST FLOOR"},{"field":"street3","value":null},{"field":"city","value":"DALLAS"},{"field":"state","value":"TX"},{"field":"zip","value":"75201-2761"},{"field":"phone","value":"2146651900"},{"field":"sharesheld","value":38362336.0},{"field":"sharesheldchange","value":8826042.0},{"field":"sharesheldpercentchange","value":0.29882022436531813},{"field":"marketvalue","value":1693313511.0},{"field":"marketvaluechange","value":389581493.88},{"field":"portfoliopercent","value":0.025556565213441507},{"field":"sharesoutpercent","value":0.0591673385603918}]},{"rownum":3,"values":[{"field":"querydate","value":"6/16/2016 10:58 PM"},{"field":"issueid","value":509060},{"field":"ticker","value":"JCI"},{"field":"companyname","value":"JOHNSON CTLS INC"},{"field":"issuetitle","value":"COM"},{"field":"filerid","value":2145},{"field":"cik","value":"0000080255"},{"field":"currentreportdate","value":"3/31/2016 12:00 AM"},{"field":"priorreportdate","value":"12/31/2015 12:00 AM"},{"field":"ownername","value":"PRICE T ROWE ASSOCIATES INC /MD/"},{"field":"street1","value":"100 EAST PRATT ST"},{"field":"street2","value":null},{"field":"street3","value":null},{"field":"city","value":"BALTIMORE"},{"field":"state","value":"MD"},{"field":"zip","value":"21202"},{"field":"phone","value":"(410)345-6603"},{"field":"sharesheld","value":30882473.0},{"field":"sharesheldchange","value":-9353979.0},{"field":"sharesheldpercentchange","value":-0.23247524408961306},{"field":"marketvalue","value":1363152358.0},{"field":"marketvaluechange","value":-412884633.06},{"field":"portfoliopercent","value":0.0028695873960766869},{"field":"sharesoutpercent","value":0.047630929867596143}]},{"rownum":4,"values":[{"field":"querydate","value":"6/16/2016 10:58 PM"},{"field":"issueid","value":509060},{"field":"ticker","value":"JCI"},{"field":"companyname","value":"JOHNSON CTLS INC"},{"field":"issuetitle","value":"COM"},{"field":"filerid","value":6697},{"field":"cik","value":"0000093751"},{"field":"currentreportdate","value":"3/31/2016 12:00 AM"},{"field":"priorreportdate","value":"12/31/2015 12:00 AM"},{"field":"ownername","value":"STATE STREET CORP"},{"field":"street1","value":"ONE LINCOLN STREET"},{"field":"street2","value":null},{"field":"street3","value":null},{"field":"city","value":"BOSTON"},{"field":"state","value":"MA"},{"field":"zip","value":"02111"},{"field":"phone","value":"617 786-3000"},{"field":"sharesheld","value":26431033.0},{"field":"sharesheldchange","value":191922.0},{"field":"sharesheldpercentchange","value":0.0073143484167584793},{"field":"marketvalue","value":1166665797.0},{"field":"marketvaluechange","value":8471437.08},{"field":"portfoliopercent","value":0.001253223216264333},{"field":"sharesoutpercent","value":0.040765345416188634}]},{"rownum":5,"values":[{"field":"querydate","value":"6/16/2016 10:58 PM"},{"field":"issueid","value":509060},{"field":"ticker","value":"JCI"},{"field":"companyname","value":"JOHNSON CTLS INC"},{"field":"issuetitle","value":"COM"},{"field":"filerid","value":767200},{"field":"cik","value":"0001422848"},{"field":"currentreportdate","value":"3/31/2016 12:00 AM"},{"field":"priorreportdate","value":"12/31/2015 12:00 AM"},{"field":"ownername","value":"CAPITAL RESEARCH GLOBAL INVESTORS"},{"field":"street1","value":"333 SOUTH HOPE STREET"},{"field":"street2","value":"55TH FLOOR"},{"field":"street3","value":null},{"field":"city","value":"LOS ANGELES"},{"field":"state","value":"CA"},{"field":"zip","value":"90071"},{"field":"phone","value":"2134869200"},{"field":"sharesheld","value":23115005.0},{"field":"sharesheldchange","value":-9500000.0},{"field":"sharesheldpercentchange","value":-0.29127697512234019},{"field":"marketvalue","value":1020296321.0},{"field":"marketvaluechange","value":-419330000.0},{"field":"portfoliopercent","value":0.0035353859702550719},{"field":"sharesoutpercent","value":0.035650939678442663}]},{"rownum":6,"values":[{"field":"querydate","value":"6/16/2016 10:58 PM"},{"field":"issueid","value":509060},{"field":"ticker","value":"JCI"},{"field":"companyname","value":"JOHNSON CTLS INC"},{"field":"issuetitle","value":"COM"},{"field":"filerid","value":762271},{"field":"cik","value":"0001418333"},{"field":"currentreportdate","value":"3/31/2016 12:00 AM"},{"field":"priorreportdate","value":"12/31/2015 12:00 AM"},{"field":"ownername","value":"MACQUARIE GROUP LTD"},{"field":"street1","value":"50 MARTIN PLACE"},{"field":"street2","value":null},{"field":"street3","value":null},{"field":"city","value":"SYDNEY, NSW 2000"},{"field":"state","value":null},{"field":"zip","value":"2000"},{"field":"phone","value":"212.231.1000"},{"field":"sharesheld","value":16729973.0},{"field":"sharesheldchange","value":1952330.0},{"field":"sharesheldpercentchange","value":0.13211376130821403},{"field":"marketvalue","value":738461008.0},{"field":"marketvaluechange","value":86175846.2},{"field":"portfoliopercent","value":0.014340909316171768},{"field":"sharesoutpercent","value":0.025803120451194986}]},{"rownum":7,"values":[{"field":"querydate","value":"6/16/2016 10:58 PM"},{"field":"issueid","value":509060},{"field":"ticker","value":"JCI"},{"field":"companyname","value":"JOHNSON CTLS INC"},{"field":"issuetitle","value":"COM"},{"field":"filerid","value":37652},{"field":"cik","value":"0000913414"},{"field":"currentreportdate","value":"3/31/2016 12:00 AM"},{"field":"priorreportdate","value":"12/31/2015 12:00 AM"},{"field":"ownername","value":"BLACKROCK INSTITUTIONAL TRUST COMPANY, N.A."},{"field":"street1","value":"400 HOWARD STREET"},{"field":"street2","value":null},{"field":"street3","value":null},{"field":"city","value":"SAN FRANCISCO"},{"field":"state","value":"CA"},{"field":"zip","value":"94105"},{"field":"phone","value":"4155972639"},{"field":"sharesheld","value":16547004.0},{"field":"sharesheldchange","value":-574496.0},{"field":"sharesheldpercentchange","value":-0.033554069444850045},{"field":"marketvalue","value":730384757.0},{"field":"marketvaluechange","value":-25358253.44},{"field":"portfoliopercent","value":0.001198488692014166},{"field":"sharesoutpercent","value":0.025520922079097515}]},{"rownum":8,"values":[{"field":"querydate","value":"6/16/2016 10:58 PM"},{"field":"issueid","value":509060},{"field":"ticker","value":"JCI"},{"field":"companyname","value":"JOHNSON CTLS INC"},{"field":"issuetitle","value":"COM"},{"field":"filerid","value":12291},{"field":"cik","value":"0000914208"},{"field":"currentreportdate","value":"3/31/2016 12:00 AM"},{"field":"priorreportdate","value":"12/31/2015 12:00 AM"},{"field":"ownername","value":"INVESCO LTD."},{"field":"street1","value":"1555 PEACHTREE STREET NE"},{"field":"street2","value":"SUITE 1800"},{"field":"street3","value":null},{"field":"city","value":"ATLANTA"},{"field":"state","value":"GA"},{"field":"zip","value":"30309"},{"field":"phone","value":"404-892-0896"},{"field":"sharesheld","value":14297295.0},{"field":"sharesheldchange","value":-1842912.0},{"field":"sharesheldpercentchange","value":-0.11418143521951113},{"field":"marketvalue","value":631082601.0},{"field":"marketvaluechange","value":-81346135.68},{"field":"portfoliopercent","value":0.0026232910529103461},{"field":"sharesoutpercent","value":0.022051130925989409}]},{"rownum":9,"values":[{"field":"querydate","value":"6/16/2016 10:58 PM"},{"field":"issueid","value":509060},{"field":"ticker","value":"JCI"},{"field":"companyname","value":"JOHNSON CTLS INC"},{"field":"issuetitle","value":"COM"},{"field":"filerid","value":13671},{"field":"cik","value":"0000912938"},{"field":"currentreportdate","value":"3/31/2016 12:00 AM"},{"field":"priorreportdate","value":"12/31/2015 12:00 AM"},{"field":"ownername","value":"MASSACHUSETTS FINANCIAL SERVICES CO /MA/"},{"field":"street1","value":"111 HUNTINGTON AVENUE"},{"field":"street2","value":"24TH FLOOR"},{"field":"street3","value":null},{"field":"city","value":"BOSTON"},{"field":"state","value":"MA"},{"field":"zip","value":"02199"},{"field":"phone","value":"18006372929"},{"field":"sharesheld","value":13706889.0},{"field":"sharesheldchange","value":-600534.0},{"field":"sharesheldpercentchange","value":-0.041973596503018046},{"field":"marketvalue","value":605022080.0},{"field":"marketvaluechange","value":-26507570.76},{"field":"portfoliopercent","value":0.0030982575040018022},{"field":"sharesoutpercent","value":0.021140530703675348}]},{"rownum":10,"values":[{"field":"querydate","value":"6/16/2016 10:58 PM"},{"field":"issueid","value":509060},{"field":"ticker","value":"JCI"},{"field":"companyname","value":"JOHNSON CTLS INC"},{"field":"issuetitle","value":"COM"},{"field":"filerid","value":767199},{"field":"cik","value":"0001422849"},{"field":"currentreportdate","value":"3/31/2016 12:00 AM"},{"field":"priorreportdate","value":"12/31/2015 12:00 AM"},{"field":"ownername","value":"CAPITAL WORLD INVESTORS"},{"field":"street1","value":"333 SOUTH HOPE STREET"},{"field":"street2","value":"55TH FLOOR"},{"field":"street3","value":null},{"field":"city","value":"LOS ANGELES"},{"field":"state","value":"CA"},{"field":"zip","value":"90071"},{"field":"phone","value":"2134869200"},{"field":"sharesheld","value":13608078.0},{"field":"sharesheldchange","value":4211609.0},{"field":"sharesheldpercentchange","value":0.448211876184554},{"field":"marketvalue","value":600660563.0},{"field":"marketvaluechange","value":185900421.26},{"field":"portfoliopercent","value":0.0016472801083125331},{"field":"sharesoutpercent","value":0.020988131645117213}]}]}}