{"result":{"totalrows":566,"rows":[{"rownum":1,"values":[{"field":"querydate","value":"6/16/2016 10:58 PM"},{"field":"issueid","value":510447},{"field":"ticker","value":"KSS"},{"field":"companyname","value":"KOHLS CORP"},{"field":"issuetitle","value":"COM"},{"field":"filerid","value":61322},{"field":"cik","value":"0000102909"},{"field":"currentreportdate","value":"3/31/2016 12:00 AM"},{"field":"priorreportdate","value":"12/31/2015 12:00 AM"},{"field":"ownername","value":"VANGUARD GROUP INC"},{"field":"street1","value":"PO BOX 2600"},{"field":"street2","value":"V26"},{"field":"street3","value":null},{"field":"city","value":"VALLEY FORGE"},{"field":"state","value":"PA"},{"field":"zip","value":"19482-2600"},{"field":"phone","value":"6106691000"},{"field":"sharesheld","value":16563525.0},{"field":"sharesheldchange","value":264421.0},{"field":"sharesheldpercentchange","value":0.016223039008770052},{"field":"marketvalue","value":582870445.0},{"field":"marketvaluechange","value":9304974.99},{"field":"portfoliopercent","value":0.000375166412158708},{"field":"sharesoutpercent","value":0.090161631606971632}]},{"rownum":2,"values":[{"field":"querydate","value":"6/16/2016 10:58 PM"},{"field":"issueid","value":510447},{"field":"ticker","value":"KSS"},{"field":"companyname","value":"KOHLS CORP"},{"field":"issuetitle","value":"COM"},{"field":"filerid","value":8702},{"field":"cik","value":"0000019617"},{"field":"currentreportdate","value":"3/31/2016 12:00 AM"},{"field":"priorreportdate","value":"12/31/2015 12:00 AM"},{"field":"ownername","value":"JPMORGAN CHASE & CO"},{"field":"street1","value":"270 PARK AVE"},{"field":"street2","value":"38TH FL"},{"field":"street3","value":null},{"field":"city","value":"NEW YORK"},{"field":"state","value":"NY"},{"field":"zip","value":"10017"},{"field":"phone","value":"2122706000"},{"field":"sharesheld","value":11023441.0},{"field":"sharesheldchange","value":-947356.0},{"field":"sharesheldpercentchange","value":-0.079138924501016936},{"field":"marketvalue","value":387914889.0},{"field":"marketvaluechange","value":-33337457.64},{"field":"portfoliopercent","value":0.0010625457531739219},{"field":"sharesoutpercent","value":0.060004825451296567}]},{"rownum":3,"values":[{"field":"querydate","value":"6/16/2016 10:58 PM"},{"field":"issueid","value":510447},{"field":"ticker","value":"KSS"},{"field":"companyname","value":"KOHLS CORP"},{"field":"issuetitle","value":"COM"},{"field":"filerid","value":2145},{"field":"cik","value":"0000080255"},{"field":"currentreportdate","value":"3/31/2016 12:00 AM"},{"field":"priorreportdate","value":"12/31/2015 12:00 AM"},{"field":"ownername","value":"PRICE T ROWE ASSOCIATES INC /MD/"},{"field":"street1","value":"100 EAST PRATT ST"},{"field":"street2","value":null},{"field":"street3","value":null},{"field":"city","value":"BALTIMORE"},{"field":"state","value":"MD"},{"field":"zip","value":"21202"},{"field":"phone","value":"(410)345-6603"},{"field":"sharesheld","value":9735008.0},{"field":"sharesheldchange","value":-4816625.0},{"field":"sharesheldpercentchange","value":-0.33100236928735077},{"field":"marketvalue","value":342574932.0},{"field":"marketvaluechange","value":-169497033.75},{"field":"portfoliopercent","value":0.000721158351309567},{"field":"sharesoutpercent","value":0.05299138951321785}]},{"rownum":4,"values":[{"field":"querydate","value":"6/16/2016 10:58 PM"},{"field":"issueid","value":510447},{"field":"ticker","value":"KSS"},{"field":"companyname","value":"KOHLS CORP"},{"field":"issuetitle","value":"COM"},{"field":"filerid","value":6697},{"field":"cik","value":"0000093751"},{"field":"currentreportdate","value":"3/31/2016 12:00 AM"},{"field":"priorreportdate","value":"12/31/2015 12:00 AM"},{"field":"ownername","value":"STATE STREET CORP"},{"field":"street1","value":"ONE LINCOLN STREET"},{"field":"street2","value":null},{"field":"street3","value":null},{"field":"city","value":"BOSTON"},{"field":"state","value":"MA"},{"field":"zip","value":"02111"},{"field":"phone","value":"617 786-3000"},{"field":"sharesheld","value":9419749.0},{"field":"sharesheldchange","value":-64856.0},{"field":"sharesheldpercentchange","value":-0.00683802857367281},{"field":"marketvalue","value":331480967.0},{"field":"marketvaluechange","value":-2282282.64},{"field":"portfoliopercent","value":0.000356074245651474},{"field":"sharesoutpercent","value":0.0512753136284782}]},{"rownum":5,"values":[{"field":"querydate","value":"6/16/2016 10:58 PM"},{"field":"issueid","value":510447},{"field":"ticker","value":"KSS"},{"field":"companyname","value":"KOHLS CORP"},{"field":"issuetitle","value":"COM"},{"field":"filerid","value":1878},{"field":"cik","value":"0000005272"},{"field":"currentreportdate","value":"3/31/2016 12:00 AM"},{"field":"priorreportdate","value":"12/31/2015 12:00 AM"},{"field":"ownername","value":"AMERICAN INTERNATIONAL GROUP INC"},{"field":"street1","value":"175 WATER STREET"},{"field":"street2","value":null},{"field":"street3","value":null},{"field":"city","value":"NEW YORK"},{"field":"state","value":"NY"},{"field":"zip","value":"10038"},{"field":"phone","value":"2127707000"},{"field":"sharesheld","value":7919804.0},{"field":"sharesheldchange","value":519220.0},{"field":"sharesheldpercentchange","value":0.070159327966549667},{"field":"marketvalue","value":278697903.0},{"field":"marketvaluechange","value":18271351.8},{"field":"portfoliopercent","value":0.01095245561151746},{"field":"sharesoutpercent","value":0.043110536594560656}]},{"rownum":6,"values":[{"field":"querydate","value":"6/16/2016 10:58 PM"},{"field":"issueid","value":510447},{"field":"ticker","value":"KSS"},{"field":"companyname","value":"KOHLS CORP"},{"field":"issuetitle","value":"COM"},{"field":"filerid","value":736081},{"field":"cik","value":"0001390777"},{"field":"currentreportdate","value":"3/31/2016 12:00 AM"},{"field":"priorreportdate","value":"12/31/2015 12:00 AM"},{"field":"ownername","value":"BANK OF NEW YORK MELLON CORP"},{"field":"street1","value":"225 LIBERTY STREET"},{"field":"street2","value":null},{"field":"street3","value":null},{"field":"city","value":"NEW YORK"},{"field":"state","value":"NY"},{"field":"zip","value":"10286"},{"field":"phone","value":"212-495-1784"},{"field":"sharesheld","value":7906223.0},{"field":"sharesheldchange","value":1704657.0},{"field":"sharesheldpercentchange","value":0.27487524925156},{"field":"marketvalue","value":278219987.0},{"field":"marketvaluechange","value":59986879.83},{"field":"portfoliopercent","value":0.000841731722314426},{"field":"sharesoutpercent","value":0.0430366099926535}]},{"rownum":7,"values":[{"field":"querydate","value":"6/16/2016 10:58 PM"},{"field":"issueid","value":510447},{"field":"ticker","value":"KSS"},{"field":"companyname","value":"KOHLS CORP"},{"field":"issuetitle","value":"COM"},{"field":"filerid","value":62699},{"field":"cik","value":"0001050470"},{"field":"currentreportdate","value":"3/31/2016 12:00 AM"},{"field":"priorreportdate","value":"12/31/2015 12:00 AM"},{"field":"ownername","value":"LSV ASSET MANAGEMENT"},{"field":"street1","value":"155 NORTH WACKER DRIVE"},{"field":"street2","value":"SUITE 4600"},{"field":"street3","value":null},{"field":"city","value":"CHICAGO"},{"field":"state","value":"IL"},{"field":"zip","value":"60606"},{"field":"phone","value":"312-460-2443"},{"field":"sharesheld","value":6378273.0},{"field":"sharesheldchange","value":134640.0},{"field":"sharesheldpercentchange","value":0.021564368053022975},{"field":"marketvalue","value":224451427.0},{"field":"marketvaluechange","value":4737981.6},{"field":"portfoliopercent","value":0.0047102897732989582},{"field":"sharesoutpercent","value":0.034719390981973568}]},{"rownum":8,"values":[{"field":"querydate","value":"6/16/2016 10:58 PM"},{"field":"issueid","value":510447},{"field":"ticker","value":"KSS"},{"field":"companyname","value":"KOHLS CORP"},{"field":"issuetitle","value":"COM"},{"field":"filerid","value":37652},{"field":"cik","value":"0000913414"},{"field":"currentreportdate","value":"3/31/2016 12:00 AM"},{"field":"priorreportdate","value":"12/31/2015 12:00 AM"},{"field":"ownername","value":"BLACKROCK INSTITUTIONAL TRUST COMPANY, N.A."},{"field":"street1","value":"400 HOWARD STREET"},{"field":"street2","value":null},{"field":"street3","value":null},{"field":"city","value":"SAN FRANCISCO"},{"field":"state","value":"CA"},{"field":"zip","value":"94105"},{"field":"phone","value":"4155972639"},{"field":"sharesheld","value":5731879.0},{"field":"sharesheldchange","value":383973.0},{"field":"sharesheldpercentchange","value":0.071798756373055175},{"field":"marketvalue","value":201704822.0},{"field":"marketvaluechange","value":13512009.87},{"field":"portfoliopercent","value":0.000330977537489504},{"field":"sharesoutpercent","value":0.031200820043664434}]},{"rownum":9,"values":[{"field":"querydate","value":"6/16/2016 10:58 PM"},{"field":"issueid","value":510447},{"field":"ticker","value":"KSS"},{"field":"companyname","value":"KOHLS CORP"},{"field":"issuetitle","value":"COM"},{"field":"filerid","value":12291},{"field":"cik","value":"0000914208"},{"field":"currentreportdate","value":"3/31/2016 12:00 AM"},{"field":"priorreportdate","value":"12/31/2015 12:00 AM"},{"field":"ownername","value":"INVESCO LTD."},{"field":"street1","value":"1555 PEACHTREE STREET NE"},{"field":"street2","value":"SUITE 1800"},{"field":"street3","value":null},{"field":"city","value":"ATLANTA"},{"field":"state","value":"GA"},{"field":"zip","value":"30309"},{"field":"phone","value":"404-892-0896"},{"field":"sharesheld","value":4339726.0},{"field":"sharesheldchange","value":-1328479.0},{"field":"sharesheldpercentchange","value":-0.23437384498267089},{"field":"marketvalue","value":152714958.0},{"field":"marketvaluechange","value":-46749176.01},{"field":"portfoliopercent","value":0.000634807206429352},{"field":"sharesoutpercent","value":0.023622796288060455}]},{"rownum":10,"values":[{"field":"querydate","value":"6/16/2016 10:58 PM"},{"field":"issueid","value":510447},{"field":"ticker","value":"KSS"},{"field":"companyname","value":"KOHLS CORP"},{"field":"issuetitle","value":"COM"},{"field":"filerid","value":10923},{"field":"cik","value":"0000073124"},{"field":"currentreportdate","value":"3/31/2016 12:00 AM"},{"field":"priorreportdate","value":"12/31/2015 12:00 AM"},{"field":"ownername","value":"NORTHERN TRUST CORP"},{"field":"street1","value":"50 S LASALLE ST"},{"field":"street2","value":null},{"field":"street3","value":null},{"field":"city","value":"CHICAGO"},{"field":"state","value":"IL"},{"field":"zip","value":"60603"},{"field":"phone","value":"3126306000"},{"field":"sharesheld","value":4011418.0},{"field":"sharesheldchange","value":169566.0},{"field":"sharesheldpercentchange","value":0.044136525821400721},{"field":"marketvalue","value":141161799.0},{"field":"marketvaluechange","value":5967027.54},{"field":"portfoliopercent","value":0.000460437755405198},{"field":"sharesoutpercent","value":0.021835689681850626}]}]}}