{"result":{"totalrows":629,"rows":[{"rownum":1,"values":[{"field":"querydate","value":"6/16/2016 11:00 PM"},{"field":"issueid","value":515366},{"field":"ticker","value":"MKC"},{"field":"companyname","value":"MCCORMICK & CO INC"},{"field":"issuetitle","value":"COM NON VTG"},{"field":"filerid","value":61322},{"field":"cik","value":"0000102909"},{"field":"currentreportdate","value":"3/31/2016 12:00 AM"},{"field":"priorreportdate","value":"12/31/2015 12:00 AM"},{"field":"ownername","value":"VANGUARD GROUP INC"},{"field":"street1","value":"PO BOX 2600"},{"field":"street2","value":"V26"},{"field":"street3","value":null},{"field":"city","value":"VALLEY FORGE"},{"field":"state","value":"PA"},{"field":"zip","value":"19482-2600"},{"field":"phone","value":"6106691000"},{"field":"sharesheld","value":10864654.0},{"field":"sharesheldchange","value":590222.0},{"field":"sharesheldpercentchange","value":0.0574457060010714},{"field":"marketvalue","value":1083097357.0},{"field":"marketvaluechange","value":58839231.18},{"field":"portfoliopercent","value":0.000697139051962515},{"field":"sharesoutpercent","value":0.0942517836536125}]},{"rownum":2,"values":[{"field":"querydate","value":"6/16/2016 11:00 PM"},{"field":"issueid","value":515366},{"field":"ticker","value":"MKC"},{"field":"companyname","value":"MCCORMICK & CO INC"},{"field":"issuetitle","value":"COM NON VTG"},{"field":"filerid","value":13234},{"field":"cik","value":"0000315032"},{"field":"currentreportdate","value":"3/31/2016 12:00 AM"},{"field":"priorreportdate","value":"12/31/2015 12:00 AM"},{"field":"ownername","value":"STATE FARM MUTUAL AUTOMOBILE INSURANCE CO"},{"field":"street1","value":"ONE STATE FARM PLAZA"},{"field":"street2","value":null},{"field":"street3","value":null},{"field":"city","value":"BLOOMINGTON"},{"field":"state","value":"IL"},{"field":"zip","value":"61710"},{"field":"phone","value":"309-766-8411"},{"field":"sharesheld","value":9435400.0},{"field":"sharesheldchange","value":0.0},{"field":"sharesheldpercentchange","value":0.0},{"field":"marketvalue","value":940615026.0},{"field":"marketvaluechange","value":0.0},{"field":"portfoliopercent","value":0.014262798235736122},{"field":"sharesoutpercent","value":0.08185288546559287}]},{"rownum":3,"values":[{"field":"querydate","value":"6/16/2016 11:00 PM"},{"field":"issueid","value":515366},{"field":"ticker","value":"MKC"},{"field":"companyname","value":"MCCORMICK & CO INC"},{"field":"issuetitle","value":"COM NON VTG"},{"field":"filerid","value":6697},{"field":"cik","value":"0000093751"},{"field":"currentreportdate","value":"3/31/2016 12:00 AM"},{"field":"priorreportdate","value":"12/31/2015 12:00 AM"},{"field":"ownername","value":"STATE STREET CORP"},{"field":"street1","value":"ONE LINCOLN STREET"},{"field":"street2","value":null},{"field":"street3","value":null},{"field":"city","value":"BOSTON"},{"field":"state","value":"MA"},{"field":"zip","value":"02111"},{"field":"phone","value":"617 786-3000"},{"field":"sharesheld","value":6911456.0},{"field":"sharesheldchange","value":-55628.0},{"field":"sharesheldpercentchange","value":-0.0079844020827077727},{"field":"marketvalue","value":689003049.0},{"field":"marketvaluechange","value":-5545555.32},{"field":"portfoliopercent","value":0.000740121652065293},{"field":"sharesoutpercent","value":0.059957459818183081}]},{"rownum":4,"values":[{"field":"querydate","value":"6/16/2016 11:00 PM"},{"field":"issueid","value":515366},{"field":"ticker","value":"MKC"},{"field":"companyname","value":"MCCORMICK & CO INC"},{"field":"issuetitle","value":"COM NON VTG"},{"field":"filerid","value":37652},{"field":"cik","value":"0000913414"},{"field":"currentreportdate","value":"3/31/2016 12:00 AM"},{"field":"priorreportdate","value":"12/31/2015 12:00 AM"},{"field":"ownername","value":"BLACKROCK INSTITUTIONAL TRUST COMPANY, N.A."},{"field":"street1","value":"400 HOWARD STREET"},{"field":"street2","value":null},{"field":"street3","value":null},{"field":"city","value":"SAN FRANCISCO"},{"field":"state","value":"CA"},{"field":"zip","value":"94105"},{"field":"phone","value":"4155972639"},{"field":"sharesheld","value":3882526.0},{"field":"sharesheldchange","value":515435.0},{"field":"sharesheldpercentchange","value":0.153080210781354},{"field":"marketvalue","value":387049017.0},{"field":"marketvaluechange","value":51383715.15},{"field":"portfoliopercent","value":0.000635108914423441},{"field":"sharesoutpercent","value":0.033681238314770594}]},{"rownum":5,"values":[{"field":"querydate","value":"6/16/2016 11:00 PM"},{"field":"issueid","value":515366},{"field":"ticker","value":"MKC"},{"field":"companyname","value":"MCCORMICK & CO INC"},{"field":"issuetitle","value":"COM NON VTG"},{"field":"filerid","value":11158},{"field":"cik","value":"0000886982"},{"field":"currentreportdate","value":"3/31/2016 12:00 AM"},{"field":"priorreportdate","value":"12/31/2015 12:00 AM"},{"field":"ownername","value":"GOLDMAN SACHS GROUP INC"},{"field":"street1","value":"200 WEST STREET"},{"field":"street2","value":null},{"field":"street3","value":null},{"field":"city","value":"NEW YORK"},{"field":"state","value":"NY"},{"field":"zip","value":"10282"},{"field":"phone","value":"2129021000"},{"field":"sharesheld","value":3675553.0},{"field":"sharesheldchange","value":-654817.0},{"field":"sharesheldpercentchange","value":-0.15121502319663216},{"field":"marketvalue","value":366415879.0},{"field":"marketvaluechange","value":-65278706.73},{"field":"portfoliopercent","value":0.001489478640753158},{"field":"sharesoutpercent","value":0.031885730200279405}]},{"rownum":6,"values":[{"field":"querydate","value":"6/16/2016 11:00 PM"},{"field":"issueid","value":515366},{"field":"ticker","value":"MKC"},{"field":"companyname","value":"MCCORMICK & CO INC"},{"field":"issuetitle","value":"COM NON VTG"},{"field":"filerid","value":110937},{"field":"cik","value":"0001006249"},{"field":"currentreportdate","value":"3/31/2016 12:00 AM"},{"field":"priorreportdate","value":"12/31/2015 12:00 AM"},{"field":"ownername","value":"BLACKROCK FUND ADVISORS"},{"field":"street1","value":"400 HOWARD STREET"},{"field":"street2","value":null},{"field":"street3","value":null},{"field":"city","value":"SAN FRANCISCO"},{"field":"state","value":"CA"},{"field":"zip","value":"94105"},{"field":"phone","value":"3027913048"},{"field":"sharesheld","value":2860375.0},{"field":"sharesheldchange","value":250153.0},{"field":"sharesheldpercentchange","value":0.095835909742542968},{"field":"marketvalue","value":285150784.0},{"field":"marketvaluechange","value":24937752.57},{"field":"portfoliopercent","value":0.000654507370543162},{"field":"sharesoutpercent","value":0.024813992757450158}]},{"rownum":7,"values":[{"field":"querydate","value":"6/16/2016 11:00 PM"},{"field":"issueid","value":515366},{"field":"ticker","value":"MKC"},{"field":"companyname","value":"MCCORMICK & CO INC"},{"field":"issuetitle","value":"COM NON VTG"},{"field":"filerid","value":63063},{"field":"cik","value":"0000948669"},{"field":"currentreportdate","value":"3/31/2016 12:00 AM"},{"field":"priorreportdate","value":"12/31/2015 12:00 AM"},{"field":"ownername","value":"PARNASSUS INVESTMENTS /CA"},{"field":"street1","value":"1 MARKET STREET #1600"},{"field":"street2","value":null},{"field":"street3","value":null},{"field":"city","value":"SAN FRANCISCO"},{"field":"state","value":"CA"},{"field":"zip","value":"94105"},{"field":"phone","value":"4157780200"},{"field":"sharesheld","value":2825210.0},{"field":"sharesheldchange","value":19412.0},{"field":"sharesheldpercentchange","value":0.0069185308422060323},{"field":"marketvalue","value":281645185.0},{"field":"marketvaluechange","value":1935182.28},{"field":"portfoliopercent","value":0.018007538841897382},{"field":"sharesoutpercent","value":0.024508933436446535}]},{"rownum":8,"values":[{"field":"querydate","value":"6/16/2016 11:00 PM"},{"field":"issueid","value":515366},{"field":"ticker","value":"MKC"},{"field":"companyname","value":"MCCORMICK & CO INC"},{"field":"issuetitle","value":"COM NON VTG"},{"field":"filerid","value":2145},{"field":"cik","value":"0000080255"},{"field":"currentreportdate","value":"3/31/2016 12:00 AM"},{"field":"priorreportdate","value":"12/31/2015 12:00 AM"},{"field":"ownername","value":"PRICE T ROWE ASSOCIATES INC /MD/"},{"field":"street1","value":"100 EAST PRATT ST"},{"field":"street2","value":null},{"field":"street3","value":null},{"field":"city","value":"BALTIMORE"},{"field":"state","value":"MD"},{"field":"zip","value":"21202"},{"field":"phone","value":"(410)345-6603"},{"field":"sharesheld","value":2708075.0},{"field":"sharesheldchange","value":109143.0},{"field":"sharesheldpercentchange","value":0.041995327311372517},{"field":"marketvalue","value":269967997.0},{"field":"marketvaluechange","value":10880465.67},{"field":"portfoliopercent","value":0.000568312673919953},{"field":"sharesoutpercent","value":0.023492777498276218}]},{"rownum":9,"values":[{"field":"querydate","value":"6/16/2016 11:00 PM"},{"field":"issueid","value":515366},{"field":"ticker","value":"MKC"},{"field":"companyname","value":"MCCORMICK & CO INC"},{"field":"issuetitle","value":"COM NON VTG"},{"field":"filerid","value":8481},{"field":"cik","value":"0000038777"},{"field":"currentreportdate","value":"3/31/2016 12:00 AM"},{"field":"priorreportdate","value":"12/31/2015 12:00 AM"},{"field":"ownername","value":"FRANKLIN RESOURCES INC"},{"field":"street1","value":"ONE FRANKLIN PARKWAY"},{"field":"street2","value":"BUILDING 920"},{"field":"street3","value":null},{"field":"city","value":"SAN MATEO"},{"field":"state","value":"CA"},{"field":"zip","value":"94403"},{"field":"phone","value":"650-312-2000"},{"field":"sharesheld","value":2628162.0},{"field":"sharesheldchange","value":20601.0},{"field":"sharesheldpercentchange","value":0.0079004863165233717},{"field":"marketvalue","value":262001470.0},{"field":"marketvaluechange","value":2053713.69},{"field":"portfoliopercent","value":0.0013864268924267419},{"field":"sharesoutpercent","value":0.022799525528437958}]},{"rownum":10,"values":[{"field":"querydate","value":"6/16/2016 11:00 PM"},{"field":"issueid","value":515366},{"field":"ticker","value":"MKC"},{"field":"companyname","value":"MCCORMICK & CO INC"},{"field":"issuetitle","value":"COM NON VTG"},{"field":"filerid","value":10923},{"field":"cik","value":"0000073124"},{"field":"currentreportdate","value":"3/31/2016 12:00 AM"},{"field":"priorreportdate","value":"12/31/2015 12:00 AM"},{"field":"ownername","value":"NORTHERN TRUST CORP"},{"field":"street1","value":"50 S LASALLE ST"},{"field":"street2","value":null},{"field":"street3","value":null},{"field":"city","value":"CHICAGO"},{"field":"state","value":"IL"},{"field":"zip","value":"60603"},{"field":"phone","value":"3126306000"},{"field":"sharesheld","value":1669285.0},{"field":"sharesheldchange","value":7391.0},{"field":"sharesheldpercentchange","value":0.0044473353896217213},{"field":"marketvalue","value":166411022.0},{"field":"marketvaluechange","value":736808.79},{"field":"portfoliopercent","value":0.000542794991188551},{"field":"sharesoutpercent","value":0.014481187221997181}]}]}}